hatch_cython/__about__.py
hatch_cython/__init__.py
hatch_cython/constants.py
hatch_cython/devel.py
hatch_cython/hooks.py
hatch_cython/plugin.py
hatch_cython/temp.py
hatch_cython/types.py
hatch_cython/utils.py
hatch_cython/config/__init__.py
hatch_cython/config/autoimport.py
hatch_cython/config/config.py
hatch_cython/config/defaults.py
hatch_cython/config/files.py
hatch_cython/config/flags.py
hatch_cython/config/includes.py
hatch_cython/config/macros.py
hatch_cython/config/platform.py
hatch_cython/config/templates.py
hatch_cython-0.6.0.dist-info/METADATA
hatch_cython-0.6.0.dist-info/WHEEL
hatch_cython-0.6.0.dist-info/entry_points.txt
hatch_cython-0.6.0.dist-info/licenses/LICENSE.txt
hatch_cython-0.6.0.dist-info/RECORD
