Metadata-Version: 2.4
Name: hatch-cython
Version: 0.6.0
Summary: Cython build hooks for hatch
Project-URL: Documentation, https://github.com/joshua-auchincloss/hatch-cython#readme
Project-URL: Issues, https://github.com/joshua-auchincloss/hatch-cython/issues
Project-URL: Source, https://github.com/joshua-auchincloss/hatch-cython
Author-email: joshua-auchincloss <joshua.auchincloss@proton.me>
License-Expression: MIT
License-File: LICENSE.txt
Classifier: Development Status :: 4 - Beta
Classifier: License :: OSI Approved :: MIT License
Classifier: Programming Language :: Python
Classifier: Programming Language :: Python :: 3.8
Classifier: Programming Language :: Python :: 3.9
Classifier: Programming Language :: Python :: 3.10
Classifier: Programming Language :: Python :: 3.11
Classifier: Programming Language :: Python :: 3.12
Classifier: Programming Language :: Python :: 3.13
Classifier: Programming Language :: Python :: Implementation :: CPython
Classifier: Programming Language :: Python :: Implementation :: PyPy
Classifier: Topic :: Software Development :: Build Tools
Classifier: Topic :: Software Development :: Code Generators
Classifier: Topic :: Software Development :: Compilers
Requires-Python: >=3.8
Requires-Dist: cython
Requires-Dist: hatchling
Requires-Dist: setuptools
Requires-Dist: typing-extensions; python_version < '3.10'
Provides-Extra: test
Requires-Dist: coverage[toml]; extra == 'test'
Requires-Dist: numpy; extra == 'test'
Requires-Dist: pytest; extra == 'test'
Requires-Dist: pytest-cov; extra == 'test'
Requires-Dist: toml; extra == 'test'
